MANIFEST.in
RELEASE-VERSION
pavement.py
paver-minilib.zip
requirements.txt
setup.py
version.py
cythrust/__init__.pxd
cythrust/__init__.py
cythrust/describe.cpp
cythrust/describe.pxd
cythrust/describe.pyx
cythrust/functional.cpp
cythrust/functional.pxd
cythrust/functional.pyx
cythrust/random.pxd
cythrust/reduce.cpp
cythrust/reduce.pyx
cythrust/si_prefix.cpp
cythrust/si_prefix.pxd
cythrust/si_prefix.pyx
cythrust/sparse.cpp
cythrust/sparse.pyx
cythrust/utility.py
cythrust.egg-info/PKG-INFO
cythrust.egg-info/SOURCES.txt
cythrust.egg-info/dependency_links.txt
cythrust.egg-info/requires.txt
cythrust.egg-info/top_level.txt
cythrust/cuda/__init__.pxd
cythrust/cuda/__init__.py
cythrust/cuda/cycudart.cu
cythrust/cuda/cycudart.pxd
cythrust/cuda/cycudart.pyx
cythrust/cuda/device_vector/__init__.pxd
cythrust/cuda/device_vector/__init__.pxdt
cythrust/cuda/device_vector/__init__.py
cythrust/cuda/device_vector/__init__.pyt
cythrust/cuda/device_vector/copy.cu
cythrust/cuda/device_vector/copy.pyx
cythrust/cuda/device_vector/copy.pyxt
cythrust/cuda/device_vector/count.cu
cythrust/cuda/device_vector/count.pyx
cythrust/cuda/device_vector/count.pyxt
cythrust/cuda/device_vector/device_vector.pxdt
cythrust/cuda/device_vector/device_vector.pyxt
cythrust/cuda/device_vector/dtype.__init__.pyt
cythrust/cuda/device_vector/extrema.cu
cythrust/cuda/device_vector/extrema.pyx
cythrust/cuda/device_vector/extrema.pyxt
cythrust/cuda/device_vector/partition.cu
cythrust/cuda/device_vector/partition.pyx
cythrust/cuda/device_vector/partition.pyxt
cythrust/cuda/device_vector/sort.cu
cythrust/cuda/device_vector/sort.pyx
cythrust/cuda/device_vector/sort.pyxt
cythrust/cuda/device_vector/sum.cu
cythrust/cuda/device_vector/sum.pyx
cythrust/cuda/device_vector/sum.pyxt
cythrust/cuda/device_vector/float32/__init__.py
cythrust/cuda/device_vector/float32/device_vector.cu
cythrust/cuda/device_vector/float32/device_vector.pxd
cythrust/cuda/device_vector/float32/device_vector.pyx
cythrust/cuda/device_vector/float64/__init__.py
cythrust/cuda/device_vector/float64/device_vector.cu
cythrust/cuda/device_vector/float64/device_vector.pxd
