Metadata-Version: 1.0
Name: cythrust
Version: 0.9.post4
Summary: Cython bindings for the Thrust parallel library.
Home-page: https://github.com/cfobel/cythrust
Author: Christian Fobel
Author-email: UNKNOWN
License: GPL
Keywords: cython thrust cuda gpu numpy
Platform: UNKNOWN
